jmd_imagescraper/__init__.py
jmd_imagescraper/_nbdev.py
jmd_imagescraper/core.py
jmd_imagescraper/imagecleaner.py
jmd_imagescraper-1.0.2.dist-info/LICENSE
jmd_imagescraper-1.0.2.dist-info/METADATA
jmd_imagescraper-1.0.2.dist-info/WHEEL
jmd_imagescraper-1.0.2.dist-info/entry_points.txt
jmd_imagescraper-1.0.2.dist-info/top_level.txt
jmd_imagescraper-1.0.2.dist-info/RECORD
