Metadata-Version: 2.1
Name: jmd-imagescraper
Version: 1.0.2
Summary: Image scraper for DuckDuckGo for creating deep learning datasets
Home-page: https://github.com/joedockrill/jmd_imagescraper/tree/master/
Author: Joe Dockrill
Author-email: joedockrill@gmail.com
License: Apache Software License 2.0
Keywords: image scraper deep learning dataset
Platform: UNKNOWN
Classifier: Development Status :: 6 - Mature
Classifier: Intended Audience :: Developers
Classifier: License :: OSI Approved :: Apache Software License
Classifier: Natural Language :: English
Classifier: Programming Language :: Python :: 3.6
Classifier: Programming Language :: Python :: 3.7
Classifier: Programming Language :: Python :: 3.8
Requires-Python: >=3.6
Requires-Dist: Pillow
Requires-Dist: bs4
Requires-Dist: fastprogress
Requires-Dist: ipywidgets
Requires-Dist: pandas
Requires-Dist: pathlib
Requires-Dist: requests
